wfdcurses/__init__.py
wfdcurses/__main__.py
wfdcurses/data/MASTER.SCP
wfdcurses/data/__init__.py
wfdcurses/data/cwmacros.txt
wfdcurses/data/k6gte-wfdcurses.desktop
wfdcurses/data/k6gte.wfdcurses-128.png
wfdcurses/data/k6gte.wfdcurses-32.png
wfdcurses/data/k6gte.wfdcurses-64.png
wfdcurses/data/k6gte.wfdcurses.svg
wfdcurses/data/secname.json
wfdcurses/data/secpartial.json
wfdcurses/data/secstate.json
wfdcurses/lib/__init__.py
wfdcurses/lib/cat_interface.py
wfdcurses/lib/cwinterface.py
wfdcurses/lib/database.py
wfdcurses/lib/edittextfield.py
wfdcurses/lib/lookup.py
wfdcurses/lib/preferences.py
wfdcurses/lib/settings.py
wfdcurses/lib/version.py
wfdcurses/lib/versiontest.py
wfdcurses-24.2.19.dist-info/LICENSE.md
wfdcurses-24.2.19.dist-info/METADATA
wfdcurses-24.2.19.dist-info/WHEEL
wfdcurses-24.2.19.dist-info/entry_points.txt
wfdcurses-24.2.19.dist-info/top_level.txt
wfdcurses-24.2.19.dist-info/RECORD
