Metadata-Version: 2.1
Name: wfdcurses
Version: 24.2.19
Summary: Winter Field Day logger
Author-email: Michael Bridak <michael.bridak@gmail.com>
Project-URL: Homepage, https://github.com/mbridak/wfd_py_logger
Project-URL: Bug Tracker, https://github.com/mbridak/wfd_py_logger/issues
Classifier: Programming Language :: Python :: 3
Classifier: Development Status :: 5 - Production/Stable
Classifier: License :: OSI Approved :: GNU General Public License v3 (GPLv3)
Classifier: Environment :: Console :: Curses
Classifier: Operating System :: POSIX :: Linux
Classifier: Intended Audience :: End Users/Desktop
Classifier: Natural Language :: English
Classifier: Topic :: Communications :: Ham Radio
Requires-Python: >=3.9
License-File: LICENSE.md
Requires-Dist: requests
Requires-Dist: xmltodict
